a_selenium_click_on_coords/LICENSE
a_selenium_click_on_coords/README.MD
a_selenium_click_on_coords/__init__.py
a_selenium_click_on_coords/requirements.txt
a_selenium_click_on_coords/thirdparty.json
a_selenium_click_on_coords-0.10.dist-info/LICENSE.rst
a_selenium_click_on_coords-0.10.dist-info/METADATA
a_selenium_click_on_coords-0.10.dist-info/WHEEL
a_selenium_click_on_coords-0.10.dist-info/top_level.txt
a_selenium_click_on_coords-0.10.dist-info/RECORD
